olorenchemengine/__init__.py
olorenchemengine/__version__.py
olorenchemengine/base_class.py
olorenchemengine/basics.py
olorenchemengine/dataset.py
olorenchemengine/ensemble.py
olorenchemengine/gnn.py
olorenchemengine/hyperparameters.py
olorenchemengine/internal.py
olorenchemengine/interpret.py
olorenchemengine/manager.py
olorenchemengine/reduction.py
olorenchemengine/representations.py
olorenchemengine/splitters.py
olorenchemengine/uncertainty.py
olorenchemengine/beta/__init__.py
olorenchemengine/beta/gnn.py
olorenchemengine/beta/representations.py
olorenchemengine/external/__init__.py
olorenchemengine/external/piCalculax.py
olorenchemengine/external/stoned.py
olorenchemengine/external/ChemProp/__init__.py
olorenchemengine/external/ChemProp/main.py
olorenchemengine/external/GINNetwork/__init__.py
olorenchemengine/external/GINNetwork/main.py
olorenchemengine/external/GINNetwork/operations.py
olorenchemengine/external/GaussianProcess/__init__.py
olorenchemengine/external/GaussianProcess/main.py
olorenchemengine/external/HondaSTRep/__init__.py
olorenchemengine/external/HondaSTRep/main.py
olorenchemengine/external/HondaSTRep/operations.py
olorenchemengine/external/MolCLR/__init__.py
olorenchemengine/external/MolCLR/main.py
olorenchemengine/external/MolCLR/model.py
olorenchemengine/external/SPGNN/__init__.py
olorenchemengine/external/SPGNN/main.py
olorenchemengine/external/SPGNN/model.py
olorenchemengine/external/mol2vec/__init__.py
olorenchemengine/external/mol2vec/main.py
olorenchemengine/external/mol2vec/operations.py
olorenchemengine/pyg/gcn.py
olorenchemengine/pyg/util.py
olorenchemengine/visualizations/__init__.py
olorenchemengine/visualizations/attribute_section.py
olorenchemengine/visualizations/compounds.py
olorenchemengine/visualizations/exploratory_analysis.py
olorenchemengine/visualizations/matched_pairs.py
olorenchemengine/visualizations/model_comparisons.py
olorenchemengine/visualizations/visualization.py
olorenchemengine-1.0.14.dist-info/METADATA
olorenchemengine-1.0.14.dist-info/WHEEL
olorenchemengine-1.0.14.dist-info/top_level.txt
olorenchemengine-1.0.14.dist-info/RECORD
