Metadata-Version: 2.1
Name: olorenchemengine
Version: 1.0.14
Summary: Oloren ChemEngine is a library for molecular property prediction, uncertainty quantification and interpretability. It includes 50+ models and molecular representations under a unified API, which achieves state-of-the-art performances on a variety of molecular property prediction tasks. The diversity of models and representations is achieved by integrating all top-performing methods in the literature as well an in-house methods.
Home-page: https://github.com/Oloren-AI/olorenchemengine
Author: Oloren AI
Author-email: contact@oloren.ai
Platform: any
Classifier: Development Status :: 4 - Beta
Classifier: Programming Language :: Python
Requires-Dist: ipython
Requires-Dist: typing-extensions
Requires-Dist: pandas
Requires-Dist: google-cloud-firestore
Requires-Dist: pyrebase4
Requires-Dist: importlib-metadata ; python_version < "3.8"
Provides-Extra: full
Requires-Dist: ipython ; extra == 'full'
Requires-Dist: typing-extensions ; extra == 'full'
Requires-Dist: pandas ; extra == 'full'
Requires-Dist: google-cloud-firestore ; extra == 'full'
Requires-Dist: pyrebase4 ; extra == 'full'
Requires-Dist: google-auth-oauthlib <0.5 ; extra == 'full'
Requires-Dist: pytorch-lightning <=1.6.2 ; extra == 'full'
Requires-Dist: Cython ; extra == 'full'
Requires-Dist: gspread ; extra == 'full'
Requires-Dist: scikit-learn ==1.2.2 ; extra == 'full'
Requires-Dist: descriptastorus ; extra == 'full'
Requires-Dist: pytest-cov ; extra == 'full'
Requires-Dist: firebase-admin ; extra == 'full'
Requires-Dist: pytest-timeout ; extra == 'full'
Requires-Dist: sphinx ; extra == 'full'
Requires-Dist: furo ; extra == 'full'
Requires-Dist: hyperopt ; extra == 'full'
Requires-Dist: google-cloud-storage ; extra == 'full'
Requires-Dist: gcsfs ; extra == 'full'
Requires-Dist: ogb ==1.3.4 ; extra == 'full'
Requires-Dist: plotly ; extra == 'full'
Requires-Dist: xgboost ==1.4.2 ; extra == 'full'
Requires-Dist: protobuf ==3.20.1 ; extra == 'full'
Requires-Dist: pytorch-lightning ==1.4.1 ; extra == 'full'
Requires-Dist: torchmetrics ==0.6.0 ; extra == 'full'
Requires-Dist: tensorboard ; extra == 'full'
Requires-Dist: pubchempy ; extra == 'full'
Requires-Dist: gensim ; extra == 'full'
Requires-Dist: mordred ; extra == 'full'
Requires-Dist: selfies ; extra == 'full'
Provides-Extra: testing
Requires-Dist: setuptools ; extra == 'testing'
Requires-Dist: pytest ; extra == 'testing'
Requires-Dist: pytest-cov ; extra == 'testing'
